MANIFEST.in
README.md
VERSION
requirements.txt
setup.py
mongodb_streams/__init__.py
mongodb_streams/__main__.py
mongodb_streams/accumulate_by_key.py
mongodb_streams/batcher.py
mongodb_streams/events.py
mongodb_streams/io.py
mongodb_streams/logger.py
mongodb_streams/mongo.py
mongodb_streams/query.py
mongodb_streams/support.py
mongodb_streams/watcher.py
mongodb_streams/window.py
mongodb_streams.egg-info/PKG-INFO
mongodb_streams.egg-info/SOURCES.txt
mongodb_streams.egg-info/dependency_links.txt
mongodb_streams.egg-info/requires.txt
mongodb_streams.egg-info/top_level.txt